teal/__init__.py
teal/amq.py
teal/logging.py
teal/py.typed
teal/redis.py
teal/web_listener/__init__.py
teal/web_listener/asgi.py
teal/web_listener/config.py
teal/web_listener/exceptions.py
teal/web_listener/py.typed
teal/web_listener/static/favicon.ico
teal/web_listener/static/favicon.png
teal/web_listener/static/robots.txt
teal/web_listener/templates/fragment.html
teal/web_listener/utils.py
teal/websocket_dispatcher/__init__.py
teal/websocket_dispatcher/asgi.py
teal/websocket_dispatcher/config.py
teal/websocket_dispatcher/protocol.py
teal/websocket_dispatcher/py.typed
teal/websocket_dispatcher/utils.py
teapots_teal-0.5.2.dist-info/LICENSE.txt
teapots_teal-0.5.2.dist-info/METADATA
teapots_teal-0.5.2.dist-info/WHEEL
teapots_teal-0.5.2.dist-info/RECORD
