Metadata-Version: 2.1
Name: teapots-teal
Version: 0.5.2
Summary: Teacups Listener for ping, push and callback events
Home-page: https://teal.teapots.fr/
Author: Thomas Touhey
Author-email: thomas@touhey.fr
Requires-Python: >=3.11,<4.0
Classifier: Development Status :: 3 - Alpha
Classifier: Intended Audience :: Developers
Classifier: License :: OSI Approved :: CEA CNRS Inria Logiciel Libre License, version 2.1 (CeCILL-2.1)
Classifier: Natural Language :: English
Classifier: Programming Language :: Python :: 3
Classifier: Programming Language :: Python :: 3.11
Classifier: Programming Language :: Python :: 3 :: Only
Classifier: Topic :: Communications
Classifier: Typing :: Typed
Requires-Dist: aio-pika (>=9.0.5,<10.0.0)
Requires-Dist: fastapi (>=0.94.1,<0.95.0)
Requires-Dist: jinja2 (>=3.1.2,<4.0.0)
Requires-Dist: pydantic (>=1.10.6,<2.0.0)
Requires-Dist: python-json-logger (>=2.0.7,<3.0.0)
Requires-Dist: redis (>=4.5.1,<5.0.0)
Requires-Dist: websockets (>=11.0.3,<12.0.0)
Project-URL: Documentation, https://teal.teapots.fr/
Project-URL: Repository, https://gitea.teapots.fr/teapots/teal
